sisrs/__init__.py
sisrs/align_contigs.py
sisrs/change_missing.py
sisrs/command.py
sisrs/filter_nexus_for_missing.py
sisrs/get_alignment.py
sisrs/get_pruned_dict.py
sisrs/identify_fixed_sites.py
sisrs/output_alignment.py
sisrs/process.py
sisrs/sisrs.py
sisrs/specific_genome.py
sisrs/sub_sample_for_velvet_unshuff.py
sisrs/subsample.py
sisrs/aligners/__init__.py
sisrs/aligners/aligner.py
sisrs/aligners/bowtie2.py
sisrs-0.1.0.dist-info/DESCRIPTION.rst
sisrs-0.1.0.dist-info/METADATA
sisrs-0.1.0.dist-info/RECORD
sisrs-0.1.0.dist-info/WHEEL
sisrs-0.1.0.dist-info/entry_points.txt
sisrs-0.1.0.dist-info/metadata.json
sisrs-0.1.0.dist-info/top_level.txt
