Metadata-Version: 2.0
Name: sisrs
Version: 0.1.0
Summary: Site Identification from Short Read Sequences.
Home-page: https://cartwrig.ht/software/
Author: UNKNOWN
Author-email: UNKNOWN
License: GPLv3
Keywords: bioinformatics genetics
Platform: UNKNOWN
Requires-Python: >=3.6
Requires-Dist: biopython
